gov_au_theme/__init__.py
gov_au_theme/base.html
gov_au_theme/header.html
gov_au_theme/main.html
gov_au_theme/nav.html
gov_au_theme/search.html
gov_au_theme/assets/js/prism.js
gov_au_theme/assets/js/ui-kit.js
gov_au_theme/assets/latest/img/icons/arrow-right--aqua.svg
gov_au_theme/assets/latest/img/icons/arrow-right--white.svg
gov_au_theme/assets/latest/img/icons/arrow-right.svg
gov_au_theme/assets/latest/img/icons/bars.svg
gov_au_theme/assets/latest/img/icons/chevron-down--navy.svg
gov_au_theme/assets/latest/img/icons/close.svg
gov_au_theme/assets/latest/img/icons/external-link--aqua.svg
gov_au_theme/assets/latest/img/icons/logo-crest.svg
gov_au_theme/assets/latest/img/icons/logo-gov-au.svg
gov_au_theme/assets/latest/img/icons/logo-govau-full.svg
gov_au_theme/assets/stylesheets/application.css
gov_au_theme/assets/stylesheets/prism.css
gov_au_theme/assets/stylesheets/ui-kit-ie6.css
gov_au_theme/assets/stylesheets/ui-kit-ie7.css
gov_au_theme/assets/stylesheets/ui-kit-ie8.css
gov_au_theme/assets/stylesheets/ui-kit.css
mkdocs_gov_au_theme-0.1.1.dist-info/DESCRIPTION.rst
mkdocs_gov_au_theme-0.1.1.dist-info/METADATA
mkdocs_gov_au_theme-0.1.1.dist-info/RECORD
mkdocs_gov_au_theme-0.1.1.dist-info/WHEEL
mkdocs_gov_au_theme-0.1.1.dist-info/entry_points.txt
mkdocs_gov_au_theme-0.1.1.dist-info/metadata.json
mkdocs_gov_au_theme-0.1.1.dist-info/top_level.txt
