Metadata-Version: 2.0
Name: mkdocs-gov-au-theme
Version: 0.1.1
Summary: DTO UI Kit theme for MkDocs
Home-page: https://www.dto.gov.au/
Author: Digital Transformation Agency
Author-email: weboperations@digital.gov.au
License: MIT
Platform: UNKNOWN
